{
	"class" : {
		 },
	"instance" : {
		"applicationContextForOperationCode:" : "HolgerHansPeterFreyther 7/30/2014 16:28",
		"dispatchInvocation:" : "HolgerHansPeterFreyther 7/30/2014 16:29",
		"forwardSM:" : "HolgerHansPeterFreyther 7/21/2014 12:09",
		"handleSRiForSM:smscAddr:invocation:" : "HolgerHansPeterFreyther 7/30/2014 16:34",
		"homeRoutingServer:" : "HolgerHansPeterFreyther 7/16/2014 09:26",
		"initialize" : "HolgerHansPeterFreyther 7/16/2014 08:28",
		"moForwardSM:" : "HolgerHansPeterFreyther 7/21/2014 12:08",
		"mtForwardSM:" : "HolgerHansPeterFreyther 7/21/2014 12:09",
		"sendRoutingInfoForSMV2:" : "HolgerHansPeterFreyther 7/16/2014 09:34",
		"sendRoutingInfoForSMV3:" : "HolgerHansPeterFreyther 7/16/2014 09:34" } }
